<?xml version="1.0" encoding="UTF-8"?>
<CORSConfiguration xmlns="http://s3.amazonaws.com/doc/2006-03-01/">
  <CORSRule>
      <AllowedOrigin>http://localhost:3000</AllowedOrigin>
      <AllowedMethod>PUT</AllowedMethod>
      <AllowedMethod>POST</AllowedMethod>
      <AllowedMethod>DELETE</AllowedMethod>
      <AllowedMethod>GET</AllowedMethod>
      <MaxAgeSeconds>3000</MaxAgeSeconds>
      <ExposeHeader>x-amz-server-side-encryption</ExposeHeader>
      <AllowedHeader>*</AllowedHeader>
  </CORSRule>
</CORSConfiguration>
